{
  "AfD": [
    { "wort": "bürger", "tfidf": 0.000365, "rang": 1 },
    { "wort": "million", "tfidf": 0.000364, "rang": 2 },
    { "wort": "prozent", "tfidf": 0.000363, "rang": 3 },
    { "wort": "politik", "tfidf": 0.000297, "rang": 4 },
    { "wort": "grüne", "tfidf": 0.000262, "rang": 5 },
    { "wort": "wert", "tfidf": 0.000245, "rang": 6 },
    { "wort": "windindustrieanlage", "tfidf": 0.000218, "rang": 7 },
    { "wort": "national", "tfidf": 0.000189, "rang": 8 },
    { "wort": "bündnis", "tfidf": 0.000178, "rang": 9 },
    { "wort": "völlig", "tfidf": 0.000177, "rang": 10 },
    { "wort": "ampel", "tfidf": 0.000176, "rang": 11 },
    { "wort": "altpartei", "tfidf": 0.000168, "rang": 12 },
    { "wort": "unternehmen", "tfidf": 0.000159, "rang": 13 },
    { "wort": "kernenergie", "tfidf": 0.000159, "rang": 14 },
    { "wort": "staat", "tfidf": 0.000158, "rang": 15 },
    { "wort": "drei", "tfidf": 0.000154, "rang": 16 },
    { "wort": "gesetzentwurf", "tfidf": 0.000151, "rang": 17 },
    { "wort": "masseneinwanderung", "tfidf": 0.000143, "rang": 18 },
    { "wort": "grün", "tfidf": 0.000139, "rang": 19 },
    { "wort": "europäisch", "tfidf": 0.000138, "rang": 20 },
    { "wort": "hause", "tfidf": 0.000136, "rang": 21 },
    { "wort": "merkel", "tfidf": 0.000134, "rang": 22 },
    { "wort": "davon", "tfidf": 0.000133, "rang": 23 },
    { "wort": "einzig", "tfidf": 0.000115, "rang": 24 },
    { "wort": "monat", "tfidf": 0.000111, "rang": 25 },
    { "wort": "stell", "tfidf": 0.000111, "rang": 26 },
    { "wort": "hören", "tfidf": 0.00011, "rang": 27 },
    { "wort": "ökosozialistisch", "tfidf": 0.000107, "rang": 28 },
    { "wort": "stellen", "tfidf": 0.000106, "rang": 29 },
    { "wort": "lang", "tfidf": 0.000106, "rang": 30 },
    { "wort": "seite", "tfidf": 0.000105, "rang": 31 },
    { "wort": "klein", "tfidf": 0.000104, "rang": 32 },
    { "wort": "setzen", "tfidf": 0.000104, "rang": 33 },
    { "wort": "zukünftig", "tfidf": 0.000103, "rang": 34 },
    { "wort": "woche", "tfidf": 0.000103, "rang": 35 },
    { "wort": "mittlerweile", "tfidf": 9.9e-5, "rang": 36 },
    { "wort": "sicherheit", "tfidf": 9.9e-5, "rang": 37 },
    { "wort": "förderung", "tfidf": 9.7e-5, "rang": 38 },
    { "wort": "russland", "tfidf": 9.7e-5, "rang": 39 },
    { "wort": "europa", "tfidf": 9.6e-5, "rang": 40 },
    { "wort": "kurz", "tfidf": 9.6e-5, "rang": 41 },
    { "wort": "wegen", "tfidf": 9.6e-5, "rang": 42 },
    { "wort": "insbesondere", "tfidf": 9.5e-5, "rang": 43 },
    { "wort": "bundeswehr", "tfidf": 9.4e-5, "rang": 44 },
    { "wort": "artikel", "tfidf": 9.4e-5, "rang": 45 },
    { "wort": "daran", "tfidf": 9.3e-5, "rang": 46 },
    { "wort": "erhalten", "tfidf": 9.2e-5, "rang": 47 },
    { "wort": "neuen", "tfidf": 9.2e-5, "rang": 48 },
    { "wort": "öffentlich", "tfidf": 9.2e-5, "rang": 49 },
    { "wort": "deren", "tfidf": 9.1e-5, "rang": 50 },
    { "wort": "übrigens", "tfidf": 8.9e-5, "rang": 51 },
    { "wort": "demokratie", "tfidf": 8.8e-5, "rang": 52 },
    { "wort": "fall", "tfidf": 8.8e-5, "rang": 53 },
    { "wort": "minister", "tfidf": 8.7e-5, "rang": 54 },
    { "wort": "knapp", "tfidf": 8.7e-5, "rang": 55 },
    { "wort": "massiv", "tfidf": 8.6e-5, "rang": 56 },
    { "wort": "inzwischen", "tfidf": 8.6e-5, "rang": 57 },
    { "wort": "alternative", "tfidf": 8.5e-5, "rang": 58 },
    { "wort": "beide", "tfidf": 8.3e-5, "rang": 59 },
    { "wort": "international", "tfidf": 8.3e-5, "rang": 60 },
    { "wort": "zitat", "tfidf": 8.2e-5, "rang": 61 },
    { "wort": "dringend", "tfidf": 8.1e-5, "rang": 62 },
    { "wort": "illegal", "tfidf": 8.1e-5, "rang": 63 },
    { "wort": "frei", "tfidf": 8e-5, "rang": 64 },
    { "wort": "stimmen", "tfidf": 7.9e-5, "rang": 65 },
    { "wort": "energie", "tfidf": 7.9e-5, "rang": 66 },
    { "wort": "zweiter", "tfidf": 7.9e-5, "rang": 67 },
    { "wort": "opfer", "tfidf": 7.9e-5, "rang": 68 },
    { "wort": "leute", "tfidf": 7.9e-5, "rang": 69 },
    { "wort": "freiheit", "tfidf": 7.9e-5, "rang": 70 },
    { "wort": "soldat", "tfidf": 7.8e-5, "rang": 71 },
    { "wort": "kernkraft", "tfidf": 7.8e-5, "rang": 72 },
    { "wort": "fallen", "tfidf": 7.6e-5, "rang": 73 },
    { "wort": "schreiben", "tfidf": 7.6e-5, "rang": 74 },
    { "wort": "volk", "tfidf": 7.6e-5, "rang": 75 },
    { "wort": "genauso", "tfidf": 7.5e-5, "rang": 76 },
    { "wort": "staatlich", "tfidf": 7.5e-5, "rang": 77 },
    { "wort": "strom", "tfidf": 7.5e-5, "rang": 78 },
    { "wort": "steuer", "tfidf": 7.4e-5, "rang": 79 },
    { "wort": "entsprechend", "tfidf": 7.3e-5, "rang": 80 },
    { "wort": "wenig", "tfidf": 7.2e-5, "rang": 81 },
    { "wort": "russisch", "tfidf": 7.2e-5, "rang": 82 },
    { "wort": "bevölkerung", "tfidf": 7.1e-5, "rang": 83 },
    { "wort": "gegenüber", "tfidf": 7e-5, "rang": 84 },
    { "wort": "anders", "tfidf": 6.9e-5, "rang": 85 },
    { "wort": "zahl", "tfidf": 6.8e-5, "rang": 86 },
    { "wort": "wahl", "tfidf": 6.8e-5, "rang": 87 },
    { "wort": "region", "tfidf": 6.8e-5, "rang": 88 },
    { "wort": "haus", "tfidf": 6.8e-5, "rang": 89 },
    { "wort": "ziel", "tfidf": 6.7e-5, "rang": 90 },
    { "wort": "ding", "tfidf": 6.6e-5, "rang": 91 },
    { "wort": "schlecht", "tfidf": 6.6e-5, "rang": 92 },
    { "wort": "polen", "tfidf": 6.5e-5, "rang": 93 },
    { "wort": "weder", "tfidf": 6.5e-5, "rang": 94 },
    { "wort": "hellbraun", "tfidf": 6.5e-5, "rang": 95 },
    { "wort": "klimahysterie", "tfidf": 6.5e-5, "rang": 96 },
    { "wort": "habeck", "tfidf": 6.5e-5, "rang": 97 },
    { "wort": "niemand", "tfidf": 6.4e-5, "rang": 98 },
    { "wort": "besonders", "tfidf": 6.4e-5, "rang": 99 },
    { "wort": "steuerzahler", "tfidf": 6.4e-5, "rang": 100 }
  ],
  "BSW": [
    { "wort": "politik", "tfidf": 0.000364, "rang": 1 },
    { "wort": "kriegskredite", "tfidf": 0.00034, "rang": 2 },
    { "wort": "prozent", "tfidf": 0.000328, "rang": 3 },
    { "wort": "bündnis", "tfidf": 0.000328, "rang": 4 },
    { "wort": "ampel", "tfidf": 0.000313, "rang": 5 },
    { "wort": "russland", "tfidf": 0.000298, "rang": 6 },
    { "wort": "aufrüstungsprogramm", "tfidf": 0.000279, "rang": 7 },
    { "wort": "nettomigrationsraen", "tfidf": 0.000272, "rang": 8 },
    { "wort": "militäroffensiven", "tfidf": 0.000272, "rang": 9 },
    { "wort": "mentalitätsreform", "tfidf": 0.000272, "rang": 10 },
    { "wort": "weaffenstoppen", "tfidf": 0.000272, "rang": 11 },
    { "wort": "vertragswerke", "tfidf": 0.000272, "rang": 12 },
    { "wort": "aufnahmerecht", "tfidf": 0.000272, "rang": 13 },
    { "wort": "konfrontationspolitik", "tfidf": 0.000272, "rang": 14 },
    { "wort": "rousseau", "tfidf": 0.000272, "rang": 15 },
    { "wort": "medikalisierung", "tfidf": 0.000272, "rang": 16 },
    { "wort": "neuauszählung", "tfidf": 0.000272, "rang": 17 },
    { "wort": "sahra", "tfidf": 0.000262, "rang": 18 },
    { "wort": "wagenknechen", "tfidf": 0.000233, "rang": 19 },
    { "wort": "waffen", "tfidf": 0.000218, "rang": 20 },
    { "wort": "million", "tfidf": 0.000218, "rang": 21 },
    { "wort": "bürger", "tfidf": 0.000218, "rang": 22 },
    { "wort": "drei", "tfidf": 0.000204, "rang": 23 },
    { "wort": "netanjahus", "tfidf": 0.000204, "rang": 24 },
    { "wort": "kriegseintritt", "tfidf": 0.000204, "rang": 25 },
    { "wort": "stahlstandoren", "tfidf": 0.000204, "rang": 26 },
    { "wort": "klein", "tfidf": 0.000197, "rang": 27 },
    { "wort": "verehren", "tfidf": 0.000189, "rang": 28 },
    { "wort": "wenig", "tfidf": 0.000189, "rang": 29 },
    { "wort": "hochsicherheitsgefängnis", "tfidf": 0.000186, "rang": 30 },
    { "wort": "lobbys", "tfidf": 0.000186, "rang": 31 },
    { "wort": "sprechakt", "tfidf": 0.000186, "rang": 32 },
    { "wort": "bachelorstudium", "tfidf": 0.000186, "rang": 33 },
    { "wort": "masterstudium", "tfidf": 0.000186, "rang": 34 },
    { "wort": "germanium", "tfidf": 0.000186, "rang": 35 },
    { "wort": "plaza", "tfidf": 0.000186, "rang": 36 },
    { "wort": "elektrolyseanlag", "tfidf": 0.000186, "rang": 37 },
    { "wort": "standortschließung", "tfidf": 0.000186, "rang": 38 },
    { "wort": "kanonenbootpolitik", "tfidf": 0.000186, "rang": 39 },
    { "wort": "grütze", "tfidf": 0.000186, "rang": 40 },
    { "wort": "bevölkerung", "tfidf": 0.000182, "rang": 41 },
    { "wort": "inzwischen", "tfidf": 0.000175, "rang": 42 },
    { "wort": "bundeswehr", "tfidf": 0.000175, "rang": 43 },
    { "wort": "setzen", "tfidf": 0.000167, "rang": 44 },
    { "wort": "sicherheit", "tfidf": 0.000167, "rang": 45 },
    { "wort": "davon", "tfidf": 0.000167, "rang": 46 },
    { "wort": "europäisch", "tfidf": 0.000167, "rang": 47 },
    { "wort": "daran", "tfidf": 0.00016, "rang": 48 },
    { "wort": "unternehmen", "tfidf": 0.000153, "rang": 49 },
    { "wort": "dringend", "tfidf": 0.000153, "rang": 50 },
    { "wort": "öffentlich", "tfidf": 0.000153, "rang": 51 },
    { "wort": "militäreinsatz", "tfidf": 0.00015, "rang": 52 },
    { "wort": "friedensgebot", "tfidf": 0.00015, "rang": 53 },
    { "wort": "lang", "tfidf": 0.000146, "rang": 54 },
    { "wort": "frieden", "tfidf": 0.000146, "rang": 55 },
    { "wort": "bologna", "tfidf": 0.000145, "rang": 56 },
    { "wort": "übrigens", "tfidf": 0.000138, "rang": 57 },
    { "wort": "vernünftig", "tfidf": 0.000138, "rang": 58 },
    { "wort": "leute", "tfidf": 0.000138, "rang": 59 },
    { "wort": "mindestlohn", "tfidf": 0.000138, "rang": 60 },
    { "wort": "international", "tfidf": 0.000138, "rang": 61 },
    { "wort": "stellen", "tfidf": 0.000138, "rang": 62 },
    { "wort": "woche", "tfidf": 0.000138, "rang": 63 },
    { "wort": "offenbar", "tfidf": 0.000138, "rang": 64 },
    { "wort": "bissch", "tfidf": 0.000138, "rang": 65 },
    { "wort": "wahl", "tfidf": 0.000138, "rang": 66 },
    { "wort": "industriepreise", "tfidf": 0.000136, "rang": 67 },
    { "wort": "schaufensterscheibe", "tfidf": 0.000136, "rang": 68 },
    { "wort": "fieberrausch", "tfidf": 0.000136, "rang": 69 },
    { "wort": "remarque", "tfidf": 0.000136, "rang": 70 },
    { "wort": "eisstand", "tfidf": 0.000136, "rang": 71 },
    { "wort": "restbetrag", "tfidf": 0.000136, "rang": 72 },
    { "wort": "schweinegrippe", "tfidf": 0.000136, "rang": 73 },
    { "wort": "pandemieverträge", "tfidf": 0.000136, "rang": 74 },
    { "wort": "impfstoffdeals", "tfidf": 0.000136, "rang": 75 },
    { "wort": "deindustrialisierungswell", "tfidf": 0.000136, "rang": 76 },
    { "wort": "sattelfest", "tfidf": 0.000136, "rang": 77 },
    { "wort": "tuchel", "tfidf": 0.000136, "rang": 78 },
    { "wort": "landoperation", "tfidf": 0.000136, "rang": 79 },
    { "wort": "militärabenteuer", "tfidf": 0.000136, "rang": 80 },
    { "wort": "teillegalisierung", "tfidf": 0.000136, "rang": 81 },
    { "wort": "psychosomatik", "tfidf": 0.000136, "rang": 82 },
    { "wort": "reifungsprozesse", "tfidf": 0.000136, "rang": 83 },
    { "wort": "fürsorgefunktion", "tfidf": 0.000136, "rang": 84 },
    { "wort": "kertsch", "tfidf": 0.000136, "rang": 85 },
    { "wort": "extrasteuer", "tfidf": 0.000136, "rang": 86 },
    { "wort": "fleischpreise", "tfidf": 0.000136, "rang": 87 },
    { "wort": "belausch", "tfidf": 0.000136, "rang": 88 },
    { "wort": "waffenantrag", "tfidf": 0.000136, "rang": 89 },
    { "wort": "watschn", "tfidf": 0.000136, "rang": 90 },
    { "wort": "krankheitsformen", "tfidf": 0.000136, "rang": 91 },
    { "wort": "kriegsbegeisterung", "tfidf": 0.000136, "rang": 92 },
    { "wort": "schreibtüchtig", "tfidf": 0.000136, "rang": 93 },
    { "wort": "hightechforschung", "tfidf": 0.000136, "rang": 94 },
    { "wort": "ultrarechten", "tfidf": 0.000136, "rang": 95 },
    { "wort": "terrorhelfer", "tfidf": 0.000136, "rang": 96 },
    { "wort": "mittelmeerstrand", "tfidf": 0.000136, "rang": 97 },
    { "wort": "allermiesesen", "tfidf": 0.000136, "rang": 98 },
    { "wort": "luxemburgs", "tfidf": 0.000136, "rang": 99 },
    { "wort": "herunterred", "tfidf": 0.000136, "rang": 100 }
  ],
  "BÜNDNIS 90/­DIE GRÜNEN": [
    { "wort": "europäisch", "tfidf": 0.000277, "rang": 1 },
    { "wort": "prozent", "tfidf": 0.000217, "rang": 2 },
    { "wort": "million", "tfidf": 0.000208, "rang": 3 },
    { "wort": "unternehmen", "tfidf": 0.000191, "rang": 4 },
    { "wort": "sicherheit", "tfidf": 0.00017, "rang": 5 },
    { "wort": "stell", "tfidf": 0.000165, "rang": 6 },
    { "wort": "woche", "tfidf": 0.000165, "rang": 7 },
    { "wort": "besonders", "tfidf": 0.000164, "rang": 8 },
    { "wort": "national", "tfidf": 0.000162, "rang": 9 },
    { "wort": "europa", "tfidf": 0.000162, "rang": 10 },
    { "wort": "klimakrise", "tfidf": 0.000159, "rang": 11 },
    { "wort": "international", "tfidf": 0.000155, "rang": 12 },
    { "wort": "verantwortung", "tfidf": 0.000152, "rang": 13 },
    { "wort": "region", "tfidf": 0.000147, "rang": 14 },
    { "wort": "setzen", "tfidf": 0.000144, "rang": 15 },
    { "wort": "davon", "tfidf": 0.000139, "rang": 16 },
    { "wort": "bündnisgrün", "tfidf": 0.000137, "rang": 17 },
    { "wort": "ampel", "tfidf": 0.000136, "rang": 18 },
    { "wort": "konkret", "tfidf": 0.000136, "rang": 19 },
    { "wort": "insbesondere", "tfidf": 0.000133, "rang": 20 },
    { "wort": "klein", "tfidf": 0.000132, "rang": 21 },
    { "wort": "erneuerbar", "tfidf": 0.000131, "rang": 22 },
    { "wort": "demokratie", "tfidf": 0.000125, "rang": 23 },
    { "wort": "russisch", "tfidf": 0.000125, "rang": 24 },
    { "wort": "daran", "tfidf": 0.000124, "rang": 25 },
    { "wort": "unterstützung", "tfidf": 0.000124, "rang": 26 },
    { "wort": "gesetzentwurf", "tfidf": 0.000121, "rang": 27 },
    { "wort": "seite", "tfidf": 0.000121, "rang": 28 },
    { "wort": "situation", "tfidf": 0.000119, "rang": 29 },
    { "wort": "politik", "tfidf": 0.000118, "rang": 30 },
    { "wort": "energie", "tfidf": 0.000118, "rang": 31 },
    { "wort": "schritt", "tfidf": 0.000117, "rang": 32 },
    { "wort": "darum", "tfidf": 0.000115, "rang": 33 },
    { "wort": "drei", "tfidf": 0.000114, "rang": 34 },
    { "wort": "klimaschutz", "tfidf": 0.000112, "rang": 35 },
    { "wort": "beratung", "tfidf": 0.00011, "rang": 36 },
    { "wort": "monat", "tfidf": 0.000109, "rang": 37 },
    { "wort": "neuen", "tfidf": 0.000108, "rang": 38 },
    { "wort": "global", "tfidf": 0.000108, "rang": 39 },
    { "wort": "öffentlich", "tfidf": 0.000107, "rang": 40 },
    { "wort": "grün", "tfidf": 0.000107, "rang": 41 },
    { "wort": "ausbau", "tfidf": 0.000106, "rang": 42 },
    { "wort": "häufig", "tfidf": 0.000105, "rang": 43 },
    { "wort": "staat", "tfidf": 0.000104, "rang": 44 },
    { "wort": "förderung", "tfidf": 0.000103, "rang": 45 },
    { "wort": "schutz", "tfidf": 0.000103, "rang": 46 },
    { "wort": "zweiter", "tfidf": 0.000102, "rang": 47 },
    { "wort": "verfahren", "tfidf": 0.000101, "rang": 48 },
    { "wort": "dringend", "tfidf": 9.8e-5, "rang": 49 },
    { "wort": "ding", "tfidf": 9.8e-5, "rang": 50 },
    { "wort": "bissch", "tfidf": 9.8e-5, "rang": 51 },
    { "wort": "stellen", "tfidf": 9.6e-5, "rang": 52 },
    { "wort": "ziel", "tfidf": 9.6e-5, "rang": 53 },
    { "wort": "lang", "tfidf": 9.5e-5, "rang": 54 },
    { "wort": "digital", "tfidf": 9.2e-5, "rang": 55 },
    { "wort": "massiv", "tfidf": 9.1e-5, "rang": 56 },
    { "wort": "erhalten", "tfidf": 9e-5, "rang": 57 },
    { "wort": "haus", "tfidf": 9e-5, "rang": 58 },
    { "wort": "russland", "tfidf": 8.9e-5, "rang": 59 },
    { "wort": "reform", "tfidf": 8.9e-5, "rang": 60 },
    { "wort": "beide", "tfidf": 8.8e-5, "rang": 61 },
    { "wort": "partner", "tfidf": 8.8e-5, "rang": 62 },
    { "wort": "gespräch", "tfidf": 8.7e-5, "rang": 63 },
    { "wort": "kurz", "tfidf": 8.6e-5, "rang": 64 },
    { "wort": "ökologisch", "tfidf": 8.6e-5, "rang": 65 },
    { "wort": "jüdin", "tfidf": 8.5e-5, "rang": 66 },
    { "wort": "ehrlich", "tfidf": 8.5e-5, "rang": 67 },
    { "wort": "bringen", "tfidf": 8.5e-5, "rang": 68 },
    { "wort": "zukünftig", "tfidf": 8.5e-5, "rang": 69 },
    { "wort": "fall", "tfidf": 8.5e-5, "rang": 70 },
    { "wort": "nachhaltig", "tfidf": 8.5e-5, "rang": 71 },
    { "wort": "übrigens", "tfidf": 8.5e-5, "rang": 72 },
    { "wort": "außerdem", "tfidf": 8.4e-5, "rang": 73 },
    { "wort": "beitrag", "tfidf": 8.2e-5, "rang": 74 },
    { "wort": "entsprechend", "tfidf": 8.2e-5, "rang": 75 },
    { "wort": "einige", "tfidf": 8.2e-5, "rang": 76 },
    { "wort": "bundeswehr", "tfidf": 8.1e-5, "rang": 77 },
    { "wort": "hause", "tfidf": 8.1e-5, "rang": 78 },
    { "wort": "völlig", "tfidf": 8e-5, "rang": 79 },
    { "wort": "antwort", "tfidf": 8e-5, "rang": 80 },
    { "wort": "nutzen", "tfidf": 7.9e-5, "rang": 81 },
    { "wort": "indem", "tfidf": 7.8e-5, "rang": 82 },
    { "wort": "geflüchtet", "tfidf": 7.8e-5, "rang": 83 },
    { "wort": "wenig", "tfidf": 7.8e-5, "rang": 84 },
    { "wort": "unabhängig", "tfidf": 7.7e-5, "rang": 85 },
    { "wort": "stärk", "tfidf": 7.6e-5, "rang": 86 },
    { "wort": "stärken", "tfidf": 7.5e-5, "rang": 87 },
    { "wort": "gegenüber", "tfidf": 7.4e-5, "rang": 88 },
    { "wort": "rahmen", "tfidf": 7.4e-5, "rang": 89 },
    { "wort": "sommer", "tfidf": 7.4e-5, "rang": 90 },
    { "wort": "grüne", "tfidf": 7.4e-5, "rang": 91 },
    { "wort": "regelung", "tfidf": 7.3e-5, "rang": 92 },
    { "wort": "hören", "tfidf": 7.3e-5, "rang": 93 },
    { "wort": "guten", "tfidf": 7.1e-5, "rang": 94 },
    { "wort": "anders", "tfidf": 7e-5, "rang": 95 },
    { "wort": "bedeuten", "tfidf": 7e-5, "rang": 96 },
    { "wort": "gewalt", "tfidf": 7e-5, "rang": 97 },
    { "wort": "intensiv", "tfidf": 7e-5, "rang": 98 },
    { "wort": "einsatz", "tfidf": 7e-5, "rang": 99 },
    { "wort": "sowie", "tfidf": 7e-5, "rang": 100 }
  ],
  "CDU/CSU": [
    { "wort": "europäisch", "tfidf": 0.000296, "rang": 1 },
    { "wort": "prozent", "tfidf": 0.000279, "rang": 2 },
    { "wort": "ampel", "tfidf": 0.000267, "rang": 3 },
    { "wort": "million", "tfidf": 0.000242, "rang": 4 },
    { "wort": "woche", "tfidf": 0.000218, "rang": 5 },
    { "wort": "national", "tfidf": 0.000206, "rang": 6 },
    { "wort": "grüne", "tfidf": 0.0002, "rang": 7 },
    { "wort": "gesetzentwurf", "tfidf": 0.000187, "rang": 8 },
    { "wort": "drei", "tfidf": 0.000186, "rang": 9 },
    { "wort": "unternehmen", "tfidf": 0.000186, "rang": 10 },
    { "wort": "monat", "tfidf": 0.000176, "rang": 11 },
    { "wort": "konkret", "tfidf": 0.000167, "rang": 12 },
    { "wort": "politik", "tfidf": 0.000161, "rang": 13 },
    { "wort": "europa", "tfidf": 0.000154, "rang": 14 },
    { "wort": "entsprechend", "tfidf": 0.000152, "rang": 15 },
    { "wort": "setzen", "tfidf": 0.000149, "rang": 16 },
    { "wort": "davon", "tfidf": 0.000148, "rang": 17 },
    { "wort": "stell", "tfidf": 0.000147, "rang": 18 },
    { "wort": "insbesondere", "tfidf": 0.000145, "rang": 19 },
    { "wort": "bündnis", "tfidf": 0.00014, "rang": 20 },
    { "wort": "ding", "tfidf": 0.000136, "rang": 21 },
    { "wort": "klein", "tfidf": 0.000133, "rang": 22 },
    { "wort": "seite", "tfidf": 0.000128, "rang": 23 },
    { "wort": "zweiter", "tfidf": 0.000123, "rang": 24 },
    { "wort": "übrigens", "tfidf": 0.000121, "rang": 25 },
    { "wort": "minister", "tfidf": 0.000121, "rang": 26 },
    { "wort": "staat", "tfidf": 0.000118, "rang": 27 },
    { "wort": "antwort", "tfidf": 0.000118, "rang": 28 },
    { "wort": "beratung", "tfidf": 0.000115, "rang": 29 },
    { "wort": "region", "tfidf": 0.000114, "rang": 30 },
    { "wort": "völlig", "tfidf": 0.000113, "rang": 31 },
    { "wort": "verantwortung", "tfidf": 0.000112, "rang": 32 },
    { "wort": "international", "tfidf": 0.000112, "rang": 33 },
    { "wort": "situation", "tfidf": 0.000112, "rang": 34 },
    { "wort": "neuen", "tfidf": 0.000111, "rang": 35 },
    { "wort": "förderung", "tfidf": 0.000111, "rang": 36 },
    { "wort": "daran", "tfidf": 0.00011, "rang": 37 },
    { "wort": "hören", "tfidf": 0.000109, "rang": 38 },
    { "wort": "sicherheit", "tfidf": 0.000105, "rang": 39 },
    { "wort": "zukünftig", "tfidf": 0.000105, "rang": 40 },
    { "wort": "stellen", "tfidf": 0.000105, "rang": 41 },
    { "wort": "januar", "tfidf": 0.000104, "rang": 42 },
    { "wort": "legislaturperiode", "tfidf": 0.0001, "rang": 43 },
    { "wort": "gespräch", "tfidf": 9.9e-5, "rang": 44 },
    { "wort": "dringend", "tfidf": 9.8e-5, "rang": 45 },
    { "wort": "gegenüber", "tfidf": 9.7e-5, "rang": 46 },
    { "wort": "lang", "tfidf": 9.7e-5, "rang": 47 },
    { "wort": "verehren", "tfidf": 9.5e-5, "rang": 48 },
    { "wort": "bundeswehr", "tfidf": 9.3e-5, "rang": 49 },
    { "wort": "besonders", "tfidf": 9.3e-5, "rang": 50 },
    { "wort": "fall", "tfidf": 9.2e-5, "rang": 51 },
    { "wort": "beide", "tfidf": 9.2e-5, "rang": 52 },
    { "wort": "partner", "tfidf": 9.1e-5, "rang": 53 },
    { "wort": "öffentlich", "tfidf": 9.1e-5, "rang": 54 },
    { "wort": "bürger", "tfidf": 8.9e-5, "rang": 55 },
    { "wort": "kurz", "tfidf": 8.8e-5, "rang": 56 },
    { "wort": "unterstützung", "tfidf": 8.7e-5, "rang": 57 },
    { "wort": "ziel", "tfidf": 8.7e-5, "rang": 58 },
    { "wort": "einzig", "tfidf": 8.7e-5, "rang": 59 },
    { "wort": "wenig", "tfidf": 8.6e-5, "rang": 60 },
    { "wort": "wert", "tfidf": 8.4e-5, "rang": 61 },
    { "wort": "insofern", "tfidf": 8.3e-5, "rang": 62 },
    { "wort": "regelung", "tfidf": 8.2e-5, "rang": 63 },
    { "wort": "bissch", "tfidf": 8.1e-5, "rang": 64 },
    { "wort": "stimmen", "tfidf": 8.1e-5, "rang": 65 },
    { "wort": "digital", "tfidf": 8e-5, "rang": 66 },
    { "wort": "haus", "tfidf": 7.9e-5, "rang": 67 },
    { "wort": "gestern", "tfidf": 7.9e-5, "rang": 68 },
    { "wort": "darum", "tfidf": 7.9e-5, "rang": 69 },
    { "wort": "vertrauen", "tfidf": 7.9e-5, "rang": 70 },
    { "wort": "hause", "tfidf": 7.9e-5, "rang": 71 },
    { "wort": "angebot", "tfidf": 7.9e-5, "rang": 72 },
    { "wort": "anders", "tfidf": 7.8e-5, "rang": 73 },
    { "wort": "möglichkeit", "tfidf": 7.8e-5, "rang": 74 },
    { "wort": "belastung", "tfidf": 7.6e-5, "rang": 75 },
    { "wort": "einige", "tfidf": 7.6e-5, "rang": 76 },
    { "wort": "massiv", "tfidf": 7.5e-5, "rang": 77 },
    { "wort": "russisch", "tfidf": 7.4e-5, "rang": 78 },
    { "wort": "bringen", "tfidf": 7.4e-5, "rang": 79 },
    { "wort": "nutzen", "tfidf": 7.3e-5, "rang": 80 },
    { "wort": "verfahren", "tfidf": 7.2e-5, "rang": 81 },
    { "wort": "fehlen", "tfidf": 7.1e-5, "rang": 82 },
    { "wort": "rahmen", "tfidf": 7.1e-5, "rang": 83 },
    { "wort": "einzelplan", "tfidf": 7.1e-5, "rang": 84 },
    { "wort": "insgesamt", "tfidf": 7e-5, "rang": 85 },
    { "wort": "tagen", "tfidf": 7e-5, "rang": 86 },
    { "wort": "opfer", "tfidf": 7e-5, "rang": 87 },
    { "wort": "erhalten", "tfidf": 7e-5, "rang": 88 },
    { "wort": "schutz", "tfidf": 7e-5, "rang": 89 },
    { "wort": "russland", "tfidf": 7e-5, "rang": 90 },
    { "wort": "einsatz", "tfidf": 6.9e-5, "rang": 91 },
    { "wort": "sicht", "tfidf": 6.9e-5, "rang": 92 },
    { "wort": "ansprechen", "tfidf": 6.8e-5, "rang": 93 },
    { "wort": "zumindest", "tfidf": 6.8e-5, "rang": 94 },
    { "wort": "entwicklung", "tfidf": 6.8e-5, "rang": 95 },
    { "wort": "übrig", "tfidf": 6.8e-5, "rang": 96 },
    { "wort": "änderung", "tfidf": 6.7e-5, "rang": 97 },
    { "wort": "dezember", "tfidf": 6.7e-5, "rang": 98 },
    { "wort": "wesentlich", "tfidf": 6.7e-5, "rang": 99 },
    { "wort": "häufig", "tfidf": 6.7e-5, "rang": 100 }
  ],
  "Die Linke": [
    { "wort": "linker", "tfidf": 0.000417, "rang": 1 },
    { "wort": "prozent", "tfidf": 0.00035, "rang": 2 },
    { "wort": "million", "tfidf": 0.000334, "rang": 3 },
    { "wort": "ampel", "tfidf": 0.0002, "rang": 4 },
    { "wort": "gesetzentwurf", "tfidf": 0.00019, "rang": 5 },
    { "wort": "öffentlich", "tfidf": 0.000186, "rang": 6 },
    { "wort": "unternehmen", "tfidf": 0.000176, "rang": 7 },
    { "wort": "völlig", "tfidf": 0.000173, "rang": 8 },
    { "wort": "europäisch", "tfidf": 0.000163, "rang": 9 },
    { "wort": "dringend", "tfidf": 0.000161, "rang": 10 },
    { "wort": "mieterin", "tfidf": 0.00016, "rang": 11 },
    { "wort": "klein", "tfidf": 0.000157, "rang": 12 },
    { "wort": "grüne", "tfidf": 0.000148, "rang": 13 },
    { "wort": "davon", "tfidf": 0.000142, "rang": 14 },
    { "wort": "wenig", "tfidf": 0.000138, "rang": 15 },
    { "wort": "monat", "tfidf": 0.000134, "rang": 16 },
    { "wort": "politik", "tfidf": 0.000133, "rang": 17 },
    { "wort": "woche", "tfidf": 0.000126, "rang": 18 },
    { "wort": "lang", "tfidf": 0.000118, "rang": 19 },
    { "wort": "preiskontroll", "tfidf": 0.000118, "rang": 20 },
    { "wort": "preisaufsicht", "tfidf": 0.000118, "rang": 21 },
    { "wort": "drei", "tfidf": 0.000117, "rang": 22 },
    { "wort": "daran", "tfidf": 0.000116, "rang": 23 },
    { "wort": "wegen", "tfidf": 0.000115, "rang": 24 },
    { "wort": "förderung", "tfidf": 0.000111, "rang": 25 },
    { "wort": "insbesondere", "tfidf": 0.00011, "rang": 26 },
    { "wort": "erhalten", "tfidf": 0.000109, "rang": 27 },
    { "wort": "staat", "tfidf": 0.000108, "rang": 28 },
    { "wort": "fehlen", "tfidf": 0.000106, "rang": 29 },
    { "wort": "national", "tfidf": 0.000105, "rang": 30 },
    { "wort": "stell", "tfidf": 0.000105, "rang": 31 },
    { "wort": "bundeswehr", "tfidf": 0.000105, "rang": 32 },
    { "wort": "bündnis", "tfidf": 0.000104, "rang": 33 },
    { "wort": "außerdem", "tfidf": 0.000101, "rang": 34 },
    { "wort": "übrigens", "tfidf": 0.0001, "rang": 35 },
    { "wort": "konkret", "tfidf": 9.8e-5, "rang": 36 },
    { "wort": "besonders", "tfidf": 9.6e-5, "rang": 37 },
    { "wort": "neuen", "tfidf": 9.4e-5, "rang": 38 },
    { "wort": "sicht", "tfidf": 9.4e-5, "rang": 39 },
    { "wort": "häufig", "tfidf": 9.3e-5, "rang": 40 },
    { "wort": "schutz", "tfidf": 9e-5, "rang": 41 },
    { "wort": "bevölkerung", "tfidf": 9e-5, "rang": 42 },
    { "wort": "behörde", "tfidf": 9e-5, "rang": 43 },
    { "wort": "zweiter", "tfidf": 8.9e-5, "rang": 44 },
    { "wort": "international", "tfidf": 8.9e-5, "rang": 45 },
    { "wort": "zukünftig", "tfidf": 8.9e-5, "rang": 46 },
    { "wort": "einige", "tfidf": 8.9e-5, "rang": 47 },
    { "wort": "europa", "tfidf": 8.9e-5, "rang": 48 },
    { "wort": "ding", "tfidf": 8.7e-5, "rang": 49 },
    { "wort": "staatlich", "tfidf": 8.7e-5, "rang": 50 },
    { "wort": "russland", "tfidf": 8.7e-5, "rang": 51 },
    { "wort": "russisch", "tfidf": 8.6e-5, "rang": 52 },
    { "wort": "niemand", "tfidf": 8.6e-5, "rang": 53 },
    { "wort": "setzen", "tfidf": 8.6e-5, "rang": 54 },
    { "wort": "energie", "tfidf": 8.5e-5, "rang": 55 },
    { "wort": "wohnung", "tfidf": 8.4e-5, "rang": 56 },
    { "wort": "stimmen", "tfidf": 8.4e-5, "rang": 57 },
    { "wort": "kurz", "tfidf": 8.3e-5, "rang": 58 },
    { "wort": "situation", "tfidf": 8.1e-5, "rang": 59 },
    { "wort": "seite", "tfidf": 8.1e-5, "rang": 60 },
    { "wort": "zumindest", "tfidf": 8.1e-5, "rang": 61 },
    { "wort": "demokratie", "tfidf": 8.1e-5, "rang": 62 },
    { "wort": "hören", "tfidf": 8e-5, "rang": 63 },
    { "wort": "fall", "tfidf": 8e-5, "rang": 64 },
    { "wort": "darum", "tfidf": 8e-5, "rang": 65 },
    { "wort": "massiv", "tfidf": 8e-5, "rang": 66 },
    { "wort": "stellen", "tfidf": 8e-5, "rang": 67 },
    { "wort": "armut", "tfidf": 7.9e-5, "rang": 68 },
    { "wort": "einsatz", "tfidf": 7.9e-5, "rang": 69 },
    { "wort": "insofern", "tfidf": 7.8e-5, "rang": 70 },
    { "wort": "kindergrundsicherung", "tfidf": 7.8e-5, "rang": 71 },
    { "wort": "miet", "tfidf": 7.8e-5, "rang": 72 },
    { "wort": "konzern", "tfidf": 7.8e-5, "rang": 73 },
    { "wort": "rente", "tfidf": 7.7e-5, "rang": 74 },
    { "wort": "region", "tfidf": 7.7e-5, "rang": 75 },
    { "wort": "einzig", "tfidf": 7.5e-5, "rang": 76 },
    { "wort": "schuldenbremse", "tfidf": 7.5e-5, "rang": 77 },
    { "wort": "januar", "tfidf": 7.5e-5, "rang": 78 },
    { "wort": "bürger", "tfidf": 7.5e-5, "rang": 79 },
    { "wort": "verantwortung", "tfidf": 7.5e-5, "rang": 80 },
    { "wort": "schlecht", "tfidf": 7.4e-5, "rang": 81 },
    { "wort": "knapp", "tfidf": 7.3e-5, "rang": 82 },
    { "wort": "deren", "tfidf": 7.3e-5, "rang": 83 },
    { "wort": "weder", "tfidf": 7.2e-5, "rang": 84 },
    { "wort": "genauso", "tfidf": 7.2e-5, "rang": 85 },
    { "wort": "einkommen", "tfidf": 7.2e-5, "rang": 86 },
    { "wort": "dramatisch", "tfidf": 7.1e-5, "rang": 87 },
    { "wort": "opfer", "tfidf": 7.1e-5, "rang": 88 },
    { "wort": "minister", "tfidf": 7.1e-5, "rang": 89 },
    { "wort": "stattdessen", "tfidf": 7.1e-5, "rang": 90 },
    { "wort": "hause", "tfidf": 7e-5, "rang": 91 },
    { "wort": "nutzen", "tfidf": 7e-5, "rang": 92 },
    { "wort": "entsprechend", "tfidf": 7e-5, "rang": 93 },
    { "wort": "arbeitgeber", "tfidf": 6.9e-5, "rang": 94 },
    { "wort": "technisch", "tfidf": 6.9e-5, "rang": 95 },
    { "wort": "trotzdem", "tfidf": 6.9e-5, "rang": 96 },
    { "wort": "sicherheit", "tfidf": 6.9e-5, "rang": 97 },
    { "wort": "trotz", "tfidf": 6.9e-5, "rang": 98 },
    { "wort": "gesetzlich", "tfidf": 6.8e-5, "rang": 99 },
    { "wort": "bissch", "tfidf": 6.8e-5, "rang": 100 }
  ],
  "FDP": [
    { "wort": "europäisch", "tfidf": 0.000326, "rang": 1 },
    { "wort": "frei", "tfidf": 0.000238, "rang": 2 },
    { "wort": "prozent", "tfidf": 0.000197, "rang": 3 },
    { "wort": "national", "tfidf": 0.000196, "rang": 4 },
    { "wort": "unternehmen", "tfidf": 0.000188, "rang": 5 },
    { "wort": "europa", "tfidf": 0.000182, "rang": 6 },
    { "wort": "setzen", "tfidf": 0.000159, "rang": 7 },
    { "wort": "staat", "tfidf": 0.000158, "rang": 8 },
    { "wort": "million", "tfidf": 0.000155, "rang": 9 },
    { "wort": "demokraen", "tfidf": 0.000152, "rang": 10 },
    { "wort": "woche", "tfidf": 0.000151, "rang": 11 },
    { "wort": "international", "tfidf": 0.000149, "rang": 12 },
    { "wort": "insbesondere", "tfidf": 0.000148, "rang": 13 },
    { "wort": "stell", "tfidf": 0.000148, "rang": 14 },
    { "wort": "partner", "tfidf": 0.000146, "rang": 15 },
    { "wort": "besonders", "tfidf": 0.000141, "rang": 16 },
    { "wort": "seite", "tfidf": 0.000137, "rang": 17 },
    { "wort": "gesetzentwurf", "tfidf": 0.000136, "rang": 18 },
    { "wort": "ding", "tfidf": 0.000133, "rang": 19 },
    { "wort": "davon", "tfidf": 0.00013, "rang": 20 },
    { "wort": "verantwortung", "tfidf": 0.000128, "rang": 21 },
    { "wort": "schritt", "tfidf": 0.000127, "rang": 22 },
    { "wort": "hause", "tfidf": 0.000125, "rang": 23 },
    { "wort": "drei", "tfidf": 0.000125, "rang": 24 },
    { "wort": "politik", "tfidf": 0.000125, "rang": 25 },
    { "wort": "russisch", "tfidf": 0.000124, "rang": 26 },
    { "wort": "daran", "tfidf": 0.000122, "rang": 27 },
    { "wort": "zukünftig", "tfidf": 0.000122, "rang": 28 },
    { "wort": "ziel", "tfidf": 0.00012, "rang": 29 },
    { "wort": "entsprechend", "tfidf": 0.000117, "rang": 30 },
    { "wort": "freiheit", "tfidf": 0.000117, "rang": 31 },
    { "wort": "monat", "tfidf": 0.000115, "rang": 32 },
    { "wort": "stellen", "tfidf": 0.000114, "rang": 33 },
    { "wort": "digital", "tfidf": 0.000112, "rang": 34 },
    { "wort": "klein", "tfidf": 0.000109, "rang": 35 },
    { "wort": "beratung", "tfidf": 0.000108, "rang": 36 },
    { "wort": "übrigens", "tfidf": 0.000107, "rang": 37 },
    { "wort": "gespräch", "tfidf": 0.000107, "rang": 38 },
    { "wort": "neuen", "tfidf": 0.000107, "rang": 39 },
    { "wort": "zweiter", "tfidf": 0.000107, "rang": 40 },
    { "wort": "situation", "tfidf": 0.000107, "rang": 41 },
    { "wort": "region", "tfidf": 0.000106, "rang": 42 },
    { "wort": "sicherheit", "tfidf": 0.000105, "rang": 43 },
    { "wort": "konkret", "tfidf": 0.000104, "rang": 44 },
    { "wort": "öffentlich", "tfidf": 0.000103, "rang": 45 },
    { "wort": "russland", "tfidf": 0.000102, "rang": 46 },
    { "wort": "bürger", "tfidf": 0.000101, "rang": 47 },
    { "wort": "demokratie", "tfidf": 9.9e-5, "rang": 48 },
    { "wort": "beide", "tfidf": 9.9e-5, "rang": 49 },
    { "wort": "beitrag", "tfidf": 9.8e-5, "rang": 50 },
    { "wort": "bissch", "tfidf": 9.7e-5, "rang": 51 },
    { "wort": "häufig", "tfidf": 9.6e-5, "rang": 52 },
    { "wort": "ampel", "tfidf": 9.3e-5, "rang": 53 },
    { "wort": "bringen", "tfidf": 9.2e-5, "rang": 54 },
    { "wort": "unterstützung", "tfidf": 9.1e-5, "rang": 55 },
    { "wort": "möglichkeit", "tfidf": 9.1e-5, "rang": 56 },
    { "wort": "lang", "tfidf": 8.9e-5, "rang": 57 },
    { "wort": "fall", "tfidf": 8.9e-5, "rang": 58 },
    { "wort": "einige", "tfidf": 8.7e-5, "rang": 59 },
    { "wort": "haus", "tfidf": 8.6e-5, "rang": 60 },
    { "wort": "kurz", "tfidf": 8.6e-5, "rang": 61 },
    { "wort": "wert", "tfidf": 8.5e-5, "rang": 62 },
    { "wort": "völlig", "tfidf": 8.5e-5, "rang": 63 },
    { "wort": "erhalten", "tfidf": 8.4e-5, "rang": 64 },
    { "wort": "verfahren", "tfidf": 8.3e-5, "rang": 65 },
    { "wort": "rahmen", "tfidf": 8.2e-5, "rang": 66 },
    { "wort": "einzelplan", "tfidf": 8.2e-5, "rang": 67 },
    { "wort": "dringend", "tfidf": 8.1e-5, "rang": 68 },
    { "wort": "wenig", "tfidf": 8e-5, "rang": 69 },
    { "wort": "bundeswehr", "tfidf": 8e-5, "rang": 70 },
    { "wort": "behörde", "tfidf": 8e-5, "rang": 71 },
    { "wort": "nutzen", "tfidf": 7.9e-5, "rang": 72 },
    { "wort": "persönlich", "tfidf": 7.9e-5, "rang": 73 },
    { "wort": "außerdem", "tfidf": 7.9e-5, "rang": 74 },
    { "wort": "schutz", "tfidf": 7.8e-5, "rang": 75 },
    { "wort": "schuldenbremse", "tfidf": 7.8e-5, "rang": 76 },
    { "wort": "linker", "tfidf": 7.8e-5, "rang": 77 },
    { "wort": "soldat", "tfidf": 7.8e-5, "rang": 78 },
    { "wort": "belastung", "tfidf": 7.7e-5, "rang": 79 },
    { "wort": "sowie", "tfidf": 7.6e-5, "rang": 80 },
    { "wort": "digitalisierung", "tfidf": 7.6e-5, "rang": 81 },
    { "wort": "nachhaltig", "tfidf": 7.6e-5, "rang": 82 },
    { "wort": "gegenüber", "tfidf": 7.6e-5, "rang": 83 },
    { "wort": "indem", "tfidf": 7.5e-5, "rang": 84 },
    { "wort": "legislaturperiode", "tfidf": 7.5e-5, "rang": 85 },
    { "wort": "information", "tfidf": 7.5e-5, "rang": 86 },
    { "wort": "förderung", "tfidf": 7.3e-5, "rang": 87 },
    { "wort": "antwort", "tfidf": 7.3e-5, "rang": 88 },
    { "wort": "darum", "tfidf": 7.2e-5, "rang": 89 },
    { "wort": "intensiv", "tfidf": 7.2e-5, "rang": 90 },
    { "wort": "entwicklung", "tfidf": 7.2e-5, "rang": 91 },
    { "wort": "reform", "tfidf": 7.2e-5, "rang": 92 },
    { "wort": "wladimir", "tfidf": 7.2e-5, "rang": 93 },
    { "wort": "wesentlich", "tfidf": 7e-5, "rang": 94 },
    { "wort": "guten", "tfidf": 7e-5, "rang": 95 },
    { "wort": "richtung", "tfidf": 7e-5, "rang": 96 },
    { "wort": "unterschiedlich", "tfidf": 7e-5, "rang": 97 },
    { "wort": "angebot", "tfidf": 6.9e-5, "rang": 98 },
    { "wort": "insgesamt", "tfidf": 6.9e-5, "rang": 99 },
    { "wort": "entscheidend", "tfidf": 6.8e-5, "rang": 100 }
  ],
  "SPD": [
    { "wort": "europäisch", "tfidf": 0.000313, "rang": 1 },
    { "wort": "million", "tfidf": 0.000229, "rang": 2 },
    { "wort": "prozent", "tfidf": 0.000213, "rang": 3 },
    { "wort": "national", "tfidf": 0.000185, "rang": 4 },
    { "wort": "unternehmen", "tfidf": 0.000179, "rang": 5 },
    { "wort": "woche", "tfidf": 0.000169, "rang": 6 },
    { "wort": "international", "tfidf": 0.000168, "rang": 7 },
    { "wort": "besonders", "tfidf": 0.000159, "rang": 8 },
    { "wort": "sicherheit", "tfidf": 0.000159, "rang": 9 },
    { "wort": "europa", "tfidf": 0.000155, "rang": 10 },
    { "wort": "stell", "tfidf": 0.000152, "rang": 11 },
    { "wort": "davon", "tfidf": 0.000148, "rang": 12 },
    { "wort": "insbesondere", "tfidf": 0.000148, "rang": 13 },
    { "wort": "setzen", "tfidf": 0.000147, "rang": 14 },
    { "wort": "verantwortung", "tfidf": 0.000146, "rang": 15 },
    { "wort": "klein", "tfidf": 0.000138, "rang": 16 },
    { "wort": "seite", "tfidf": 0.000137, "rang": 17 },
    { "wort": "drei", "tfidf": 0.000133, "rang": 18 },
    { "wort": "demokratie", "tfidf": 0.000132, "rang": 19 },
    { "wort": "daran", "tfidf": 0.000128, "rang": 20 },
    { "wort": "zukünftig", "tfidf": 0.000127, "rang": 21 },
    { "wort": "energie", "tfidf": 0.000125, "rang": 22 },
    { "wort": "erneuerbar", "tfidf": 0.000124, "rang": 23 },
    { "wort": "region", "tfidf": 0.000124, "rang": 24 },
    { "wort": "öffentlich", "tfidf": 0.000123, "rang": 25 },
    { "wort": "konkret", "tfidf": 0.000122, "rang": 26 },
    { "wort": "ding", "tfidf": 0.000121, "rang": 27 },
    { "wort": "förderung", "tfidf": 0.000121, "rang": 28 },
    { "wort": "situation", "tfidf": 0.000121, "rang": 29 },
    { "wort": "unterstützung", "tfidf": 0.00012, "rang": 30 },
    { "wort": "gesetzentwurf", "tfidf": 0.000118, "rang": 31 },
    { "wort": "wert", "tfidf": 0.000117, "rang": 32 },
    { "wort": "gespräch", "tfidf": 0.000115, "rang": 33 },
    { "wort": "beratung", "tfidf": 0.000113, "rang": 34 },
    { "wort": "darum", "tfidf": 0.000113, "rang": 35 },
    { "wort": "übrigens", "tfidf": 0.000113, "rang": 36 },
    { "wort": "staat", "tfidf": 0.000112, "rang": 37 },
    { "wort": "monat", "tfidf": 0.000111, "rang": 38 },
    { "wort": "häufig", "tfidf": 0.00011, "rang": 39 },
    { "wort": "entsprechend", "tfidf": 0.000109, "rang": 40 },
    { "wort": "politik", "tfidf": 0.000109, "rang": 41 },
    { "wort": "partner", "tfidf": 0.000108, "rang": 42 },
    { "wort": "digital", "tfidf": 0.000107, "rang": 43 },
    { "wort": "verehren", "tfidf": 0.000104, "rang": 44 },
    { "wort": "neuen", "tfidf": 0.000101, "rang": 45 },
    { "wort": "schritt", "tfidf": 9.9e-5, "rang": 46 },
    { "wort": "bissch", "tfidf": 9.9e-5, "rang": 47 },
    { "wort": "stellen", "tfidf": 9.8e-5, "rang": 48 },
    { "wort": "ziel", "tfidf": 9.6e-5, "rang": 49 },
    { "wort": "kurz", "tfidf": 9.6e-5, "rang": 50 },
    { "wort": "sowie", "tfidf": 9.6e-5, "rang": 51 },
    { "wort": "außerdem", "tfidf": 9.6e-5, "rang": 52 },
    { "wort": "lang", "tfidf": 9.5e-5, "rang": 53 },
    { "wort": "einige", "tfidf": 9.4e-5, "rang": 54 },
    { "wort": "zweiter", "tfidf": 9.4e-5, "rang": 55 },
    { "wort": "ampel", "tfidf": 9.3e-5, "rang": 56 },
    { "wort": "möglichkeit", "tfidf": 9.2e-5, "rang": 57 },
    { "wort": "nachhaltig", "tfidf": 9.2e-5, "rang": 58 },
    { "wort": "fall", "tfidf": 9.1e-5, "rang": 59 },
    { "wort": "guten", "tfidf": 9.1e-5, "rang": 60 },
    { "wort": "beide", "tfidf": 9e-5, "rang": 61 },
    { "wort": "hause", "tfidf": 9e-5, "rang": 62 },
    { "wort": "schutz", "tfidf": 8.9e-5, "rang": 63 },
    { "wort": "verfahren", "tfidf": 8.8e-5, "rang": 64 },
    { "wort": "bringen", "tfidf": 8.7e-5, "rang": 65 },
    { "wort": "rahmen", "tfidf": 8.5e-5, "rang": 66 },
    { "wort": "russisch", "tfidf": 8.4e-5, "rang": 67 },
    { "wort": "insofern", "tfidf": 8.3e-5, "rang": 68 },
    { "wort": "bürger", "tfidf": 8.3e-5, "rang": 69 },
    { "wort": "ausbau", "tfidf": 8.3e-5, "rang": 70 },
    { "wort": "erhalten", "tfidf": 8e-5, "rang": 71 },
    { "wort": "indem", "tfidf": 8e-5, "rang": 72 },
    { "wort": "ampelkoalition", "tfidf": 8e-5, "rang": 73 },
    { "wort": "zusammenhalt", "tfidf": 8e-5, "rang": 74 },
    { "wort": "haus", "tfidf": 7.8e-5, "rang": 75 },
    { "wort": "nutzen", "tfidf": 7.7e-5, "rang": 76 },
    { "wort": "global", "tfidf": 7.7e-5, "rang": 77 },
    { "wort": "unterstütz", "tfidf": 7.7e-5, "rang": 78 },
    { "wort": "intensiv", "tfidf": 7.6e-5, "rang": 79 },
    { "wort": "beitrag", "tfidf": 7.6e-5, "rang": 80 },
    { "wort": "opfer", "tfidf": 7.6e-5, "rang": 81 },
    { "wort": "wenig", "tfidf": 7.4e-5, "rang": 82 },
    { "wort": "angebot", "tfidf": 7.4e-5, "rang": 83 },
    { "wort": "gesellschaftleichen", "tfidf": 7.4e-5, "rang": 84 },
    { "wort": "antwort", "tfidf": 7.4e-5, "rang": 85 },
    { "wort": "dringend", "tfidf": 7.4e-5, "rang": 86 },
    { "wort": "gegenüber", "tfidf": 7.3e-5, "rang": 87 },
    { "wort": "regelung", "tfidf": 7.3e-5, "rang": 88 },
    { "wort": "umsetzung", "tfidf": 7.2e-5, "rang": 89 },
    { "wort": "entwicklung", "tfidf": 7.2e-5, "rang": 90 },
    { "wort": "genauso", "tfidf": 7.2e-5, "rang": 91 },
    { "wort": "persönlich", "tfidf": 7.1e-5, "rang": 92 },
    { "wort": "knapp", "tfidf": 7e-5, "rang": 93 },
    { "wort": "sinn", "tfidf": 6.9e-5, "rang": 94 },
    { "wort": "stärk", "tfidf": 6.9e-5, "rang": 95 },
    { "wort": "übernehmen", "tfidf": 6.9e-5, "rang": 96 },
    { "wort": "insgesamt", "tfidf": 6.9e-5, "rang": 97 },
    { "wort": "hören", "tfidf": 6.8e-5, "rang": 98 },
    { "wort": "technisch", "tfidf": 6.8e-5, "rang": 99 },
    { "wort": "einsatz", "tfidf": 6.8e-5, "rang": 100 }
  ],
  "Unbekannt": [
    { "wort": "vergelt", "tfidf": 0.001873, "rang": 1 },
    { "wort": "coronazahlung", "tfidf": 0.001873, "rang": 2 },
    { "wort": "systemkritiker", "tfidf": 0.001873, "rang": 3 },
    { "wort": "qualifizierungsangebot", "tfidf": 0.001873, "rang": 4 },
    { "wort": "berufsbildungssystem", "tfidf": 0.001873, "rang": 5 },
    { "wort": "qualifikationsrahmens", "tfidf": 0.001873, "rang": 6 },
    { "wort": "einreiseregeln", "tfidf": 0.001873, "rang": 7 },
    { "wort": "modellstäden", "tfidf": 0.001873, "rang": 8 },
    { "wort": "schachten", "tfidf": 0.001873, "rang": 9 },
    { "wort": "abgehalfteren", "tfidf": 0.001873, "rang": 10 },
    { "wort": "celler", "tfidf": 0.001873, "rang": 11 },
    { "wort": "bundesangelegenheit", "tfidf": 0.001873, "rang": 12 },
    { "wort": "konzeptlosigkeit", "tfidf": 0.001282, "rang": 13 },
    { "wort": "aufopferungsbereitschaft", "tfidf": 0.001282, "rang": 14 },
    { "wort": "tanksäul", "tfidf": 0.001282, "rang": 15 },
    { "wort": "zeitvertreib", "tfidf": 0.001282, "rang": 16 },
    { "wort": "zurückschauen", "tfidf": 0.001282, "rang": 17 },
    { "wort": "entscheidungsbefugnis", "tfidf": 0.001282, "rang": 18 },
    { "wort": "weiterbildungsbedarf", "tfidf": 0.001282, "rang": 19 },
    { "wort": "defizitausgleich", "tfidf": 0.001282, "rang": 20 },
    { "wort": "langeweile", "tfidf": 0.000937, "rang": 21 },
    { "wort": "talentieren", "tfidf": 0.000937, "rang": 22 },
    { "wort": "helmholtz", "tfidf": 0.000937, "rang": 23 },
    { "wort": "dozenn", "tfidf": 0.000937, "rang": 24 },
    { "wort": "durchsetzungsvermög", "tfidf": 0.000691, "rang": 25 },
    { "wort": "pick", "tfidf": 0.000691, "rang": 26 },
    { "wort": "energierohstoffen", "tfidf": 0.000691, "rang": 27 },
    { "wort": "wahlerfolg", "tfidf": 0.000691, "rang": 28 },
    { "wort": "rechtsverfahren", "tfidf": 0.000691, "rang": 29 },
    { "wort": "mitgetragen", "tfidf": 0.000691, "rang": 30 },
    { "wort": "wissensstand", "tfidf": 0.000691, "rang": 31 },
    { "wort": "quereinsteig", "tfidf": 0.000691, "rang": 32 },
    { "wort": "elektriker", "tfidf": 0.000691, "rang": 33 },
    { "wort": "academic", "tfidf": 0.000691, "rang": 34 },
    { "wort": "weltsichen", "tfidf": 0.000691, "rang": 35 },
    { "wort": "vorlesungen", "tfidf": 0.000691, "rang": 36 },
    { "wort": "denunzi", "tfidf": 0.000691, "rang": 37 },
    { "wort": "gesamtkonzeption", "tfidf": 0.000691, "rang": 38 },
    { "wort": "lebhafen", "tfidf": 0.000501, "rang": 39 },
    { "wort": "aufopferungsvoll", "tfidf": 0.000501, "rang": 40 },
    { "wort": "pflegebonusgesetz", "tfidf": 0.000501, "rang": 41 },
    { "wort": "weitertragen", "tfidf": 0.000501, "rang": 42 },
    { "wort": "surfen", "tfidf": 0.000501, "rang": 43 },
    { "wort": "einzelfrag", "tfidf": 0.000501, "rang": 44 },
    { "wort": "hinwegsetz", "tfidf": 0.000501, "rang": 45 },
    { "wort": "grundgesetzkonform", "tfidf": 0.000501, "rang": 46 },
    { "wort": "parkbank", "tfidf": 0.000501, "rang": 47 },
    { "wort": "transportgewerb", "tfidf": 0.000501, "rang": 48 },
    { "wort": "schulabbrecherquote", "tfidf": 0.000501, "rang": 49 },
    { "wort": "kompetenter", "tfidf": 0.000501, "rang": 50 },
    { "wort": "roden", "tfidf": 0.000501, "rang": 51 },
    { "wort": "giessen", "tfidf": 0.000501, "rang": 52 },
    { "wort": "verfassungsrang", "tfidf": 0.000501, "rang": 53 },
    { "wort": "umfassendst", "tfidf": 0.000501, "rang": 54 },
    { "wort": "artikuli", "tfidf": 0.000501, "rang": 55 },
    { "wort": "krankenhausschließung", "tfidf": 0.000501, "rang": 56 },
    { "wort": "vorschaltgesetz", "tfidf": 0.000501, "rang": 57 },
    { "wort": "debattenbeiträgen", "tfidf": 0.000501, "rang": 58 },
    { "wort": "gemeinwesens", "tfidf": 0.000428, "rang": 59 },
    { "wort": "bildungspolitische", "tfidf": 0.000346, "rang": 60 },
    { "wort": "ungeduld", "tfidf": 0.000346, "rang": 61 },
    { "wort": "finanzzusage", "tfidf": 0.000346, "rang": 62 },
    { "wort": "destruktiven", "tfidf": 0.000346, "rang": 63 },
    { "wort": "herausfordernd", "tfidf": 0.000346, "rang": 64 },
    { "wort": "inkaufnahme", "tfidf": 0.000346, "rang": 65 },
    { "wort": "aufgehetzen", "tfidf": 0.000346, "rang": 66 },
    { "wort": "coronaleugner", "tfidf": 0.000346, "rang": 67 },
    { "wort": "wärm", "tfidf": 0.000346, "rang": 68 },
    { "wort": "verborgen", "tfidf": 0.000346, "rang": 69 },
    { "wort": "buchstabe", "tfidf": 0.000346, "rang": 70 },
    { "wort": "fortbesteh", "tfidf": 0.000346, "rang": 71 },
    { "wort": "auftragsbüch", "tfidf": 0.000346, "rang": 72 },
    { "wort": "arbeitsmigration", "tfidf": 0.000346, "rang": 73 },
    { "wort": "heidelberg", "tfidf": 0.000346, "rang": 74 },
    { "wort": "solarmodul", "tfidf": 0.000346, "rang": 75 },
    { "wort": "instagram", "tfidf": 0.000346, "rang": 76 },
    { "wort": "vätern", "tfidf": 0.000346, "rang": 77 },
    { "wort": "vermischung", "tfidf": 0.000346, "rang": 78 },
    { "wort": "einzelinteress", "tfidf": 0.000346, "rang": 79 },
    { "wort": "pluralistische", "tfidf": 0.000346, "rang": 80 },
    { "wort": "ideologe", "tfidf": 0.000346, "rang": 81 },
    { "wort": "duktus", "tfidf": 0.000346, "rang": 82 },
    { "wort": "richtigstelle", "tfidf": 0.000346, "rang": 83 },
    { "wort": "drgs", "tfidf": 0.000346, "rang": 84 },
    { "wort": "emmi", "tfidf": 0.000346, "rang": 85 },
    { "wort": "zeulner", "tfidf": 0.000346, "rang": 86 },
    { "wort": "beruflich", "tfidf": 0.000301, "rang": 87 },
    { "wort": "begrüßung", "tfidf": 0.000214, "rang": 88 },
    { "wort": "bildungspolitisch", "tfidf": 0.000214, "rang": 89 },
    { "wort": "plenarwoch", "tfidf": 0.000214, "rang": 90 },
    { "wort": "volkspartei", "tfidf": 0.000214, "rang": 91 },
    { "wort": "opportunistisch", "tfidf": 0.000214, "rang": 92 },
    { "wort": "tariflöhnen", "tfidf": 0.000214, "rang": 93 },
    { "wort": "schaufensterantrag", "tfidf": 0.000214, "rang": 94 },
    { "wort": "drüben", "tfidf": 0.000214, "rang": 95 },
    { "wort": "wechstumsprognosen", "tfidf": 0.000214, "rang": 96 },
    { "wort": "geschäftsklimaindex", "tfidf": 0.000214, "rang": 97 },
    { "wort": "durchgelesen", "tfidf": 0.000214, "rang": 98 },
    { "wort": "zündeln", "tfidf": 0.000214, "rang": 99 },
    { "wort": "originären", "tfidf": 0.000214, "rang": 100 }
  ],
  "fraktionslos": [
    { "wort": "nachfrage", "tfidf": 0.000726, "rang": 1 },
    { "wort": "europäisch", "tfidf": 0.000349, "rang": 2 },
    { "wort": "million", "tfidf": 0.000237, "rang": 3 },
    { "wort": "sicherheit", "tfidf": 0.000229, "rang": 4 },
    { "wort": "europa", "tfidf": 0.000228, "rang": 5 },
    { "wort": "prozent", "tfidf": 0.000223, "rang": 6 },
    { "wort": "fragestell", "tfidf": 0.000221, "rang": 7 },
    { "wort": "stellen", "tfidf": 0.000216, "rang": 8 },
    { "wort": "national", "tfidf": 0.000215, "rang": 9 },
    { "wort": "gespräch", "tfidf": 0.000199, "rang": 10 },
    { "wort": "partner", "tfidf": 0.000199, "rang": 11 },
    { "wort": "international", "tfidf": 0.000196, "rang": 12 },
    { "wort": "ding", "tfidf": 0.000186, "rang": 13 },
    { "wort": "unterstützung", "tfidf": 0.000175, "rang": 14 },
    { "wort": "woche", "tfidf": 0.000171, "rang": 15 },
    { "wort": "unternehmen", "tfidf": 0.00017, "rang": 16 },
    { "wort": "region", "tfidf": 0.000161, "rang": 17 },
    { "wort": "setzen", "tfidf": 0.000153, "rang": 18 },
    { "wort": "entsprechend", "tfidf": 0.000151, "rang": 19 },
    { "wort": "intensiv", "tfidf": 0.000146, "rang": 20 },
    { "wort": "davon", "tfidf": 0.000145, "rang": 21 },
    { "wort": "insbesondere", "tfidf": 0.000144, "rang": 22 },
    { "wort": "bürger", "tfidf": 0.000143, "rang": 23 },
    { "wort": "zweiter", "tfidf": 0.000141, "rang": 24 },
    { "wort": "russisch", "tfidf": 0.000139, "rang": 25 },
    { "wort": "fragestellerin", "tfidf": 0.000137, "rang": 26 },
    { "wort": "möglichkeit", "tfidf": 0.000135, "rang": 27 },
    { "wort": "konkret", "tfidf": 0.000134, "rang": 28 },
    { "wort": "drei", "tfidf": 0.000132, "rang": 29 },
    { "wort": "demokratie", "tfidf": 0.000131, "rang": 30 },
    { "wort": "beratung", "tfidf": 0.00013, "rang": 31 },
    { "wort": "insofern", "tfidf": 0.000128, "rang": 32 },
    { "wort": "daran", "tfidf": 0.000128, "rang": 33 },
    { "wort": "übrigens", "tfidf": 0.000127, "rang": 34 },
    { "wort": "besonders", "tfidf": 0.000126, "rang": 35 },
    { "wort": "staat", "tfidf": 0.000126, "rang": 36 },
    { "wort": "situation", "tfidf": 0.000125, "rang": 37 },
    { "wort": "ziel", "tfidf": 0.000124, "rang": 38 },
    { "wort": "indem", "tfidf": 0.000122, "rang": 39 },
    { "wort": "neuen", "tfidf": 0.000121, "rang": 40 },
    { "wort": "seite", "tfidf": 0.00012, "rang": 41 },
    { "wort": "monat", "tfidf": 0.00012, "rang": 42 },
    { "wort": "haus", "tfidf": 0.000118, "rang": 43 },
    { "wort": "verantwortung", "tfidf": 0.000117, "rang": 44 },
    { "wort": "darum", "tfidf": 0.000114, "rang": 45 },
    { "wort": "stell", "tfidf": 0.000113, "rang": 46 },
    { "wort": "beitrag", "tfidf": 0.000112, "rang": 47 },
    { "wort": "bundeswehr", "tfidf": 0.000112, "rang": 48 },
    { "wort": "öffentlich", "tfidf": 0.000112, "rang": 49 },
    { "wort": "schutz", "tfidf": 0.000111, "rang": 50 },
    { "wort": "förderung", "tfidf": 0.000108, "rang": 51 },
    { "wort": "russland", "tfidf": 0.000108, "rang": 52 },
    { "wort": "fall", "tfidf": 0.000106, "rang": 53 },
    { "wort": "beide", "tfidf": 0.000106, "rang": 54 },
    { "wort": "schritt", "tfidf": 0.000101, "rang": 55 },
    { "wort": "bringen", "tfidf": 0.0001, "rang": 56 },
    { "wort": "klein", "tfidf": 9.9e-5, "rang": 57 },
    { "wort": "insgesamt", "tfidf": 9.8e-5, "rang": 58 },
    { "wort": "kurz", "tfidf": 9.8e-5, "rang": 59 },
    { "wort": "nutzen", "tfidf": 9.7e-5, "rang": 60 },
    { "wort": "legislaturperiode", "tfidf": 9.7e-5, "rang": 61 },
    { "wort": "gesetzentwurf", "tfidf": 9.5e-5, "rang": 62 },
    { "wort": "unterstütz", "tfidf": 9.4e-5, "rang": 63 },
    { "wort": "soldat", "tfidf": 9.3e-5, "rang": 64 },
    { "wort": "rahmen", "tfidf": 9.2e-5, "rang": 65 },
    { "wort": "soldatin", "tfidf": 9.2e-5, "rang": 66 },
    { "wort": "antwort", "tfidf": 9.1e-5, "rang": 67 },
    { "wort": "angebot", "tfidf": 9.1e-5, "rang": 68 },
    { "wort": "digital", "tfidf": 9.1e-5, "rang": 69 },
    { "wort": "politik", "tfidf": 9e-5, "rang": 70 },
    { "wort": "lang", "tfidf": 8.9e-5, "rang": 71 },
    { "wort": "energie", "tfidf": 8.9e-5, "rang": 72 },
    { "wort": "zunächst", "tfidf": 8.8e-5, "rang": 73 },
    { "wort": "bündnis", "tfidf": 8.7e-5, "rang": 74 },
    { "wort": "januar", "tfidf": 8.6e-5, "rang": 75 },
    { "wort": "wert", "tfidf": 8.6e-5, "rang": 76 },
    { "wort": "infrastruktur", "tfidf": 8.6e-5, "rang": 77 },
    { "wort": "häufig", "tfidf": 8.6e-5, "rang": 78 },
    { "wort": "ausbau", "tfidf": 8.4e-5, "rang": 79 },
    { "wort": "opfer", "tfidf": 8.4e-5, "rang": 80 },
    { "wort": "entwicklung", "tfidf": 8.3e-5, "rang": 81 },
    { "wort": "zusammen", "tfidf": 8.2e-5, "rang": 82 },
    { "wort": "verfügung", "tfidf": 8.2e-5, "rang": 83 },
    { "wort": "künftig", "tfidf": 8.2e-5, "rang": 84 },
    { "wort": "sodass", "tfidf": 8.1e-5, "rang": 85 },
    { "wort": "unterschiedlich", "tfidf": 8.1e-5, "rang": 86 },
    { "wort": "freiheit", "tfidf": 8.1e-5, "rang": 87 },
    { "wort": "guten", "tfidf": 8.1e-5, "rang": 88 },
    { "wort": "technisch", "tfidf": 8e-5, "rang": 89 },
    { "wort": "nation", "tfidf": 7.9e-5, "rang": 90 },
    { "wort": "erneuerbar", "tfidf": 7.9e-5, "rang": 91 },
    { "wort": "ausdrücklich", "tfidf": 7.8e-5, "rang": 92 },
    { "wort": "austausch", "tfidf": 7.8e-5, "rang": 93 },
    { "wort": "reform", "tfidf": 7.7e-5, "rang": 94 },
    { "wort": "niemand", "tfidf": 7.7e-5, "rang": 95 },
    { "wort": "zusammenhalt", "tfidf": 7.7e-5, "rang": 96 },
    { "wort": "einsatz", "tfidf": 7.7e-5, "rang": 97 },
    { "wort": "anders", "tfidf": 7.6e-5, "rang": 98 },
    { "wort": "verfahren", "tfidf": 7.3e-5, "rang": 99 },
    { "wort": "derzeit", "tfidf": 7.3e-5, "rang": 100 }
  ]
}
